README.md
setup.py
MyMachineLearning_Quicker_and_Easier/__init__.py
MyMachineLearning_Quicker_and_Easier/lists_of_number.py
MyMachineLearning_Quicker_and_Easier/one_list_of_number.py
MyMachineLearning_Quicker_and_Easier.egg-info/PKG-INFO
MyMachineLearning_Quicker_and_Easier.egg-info/SOURCES.txt
MyMachineLearning_Quicker_and_Easier.egg-info/dependency_links.txt
MyMachineLearning_Quicker_and_Easier.egg-info/top_level.txt