Metadata-Version: 1.0
Name: MyMachineLearning-Quicker-and-Easier
Version: 1.0.0
Summary: The packages for the machine learning(just easily learn!) are always hard to study, and difficult to use. Now you have the MyMachineLearning_Quicker_and_Easier! It can maybe help you to use machine learning.
Home-page: https://www.python.org
Author: ETRO_secondleader
Author-email: ETRO_gfyx@163.com
License: UNKNOWN
Platform: UNKNOWN
